flexion/__init__.py
flexion/converter.py
flexion/flon.py
flexion_interpreter-1.0.2.dist-info/licenses/LICENSE
flexion_interpreter-1.0.2.dist-info/METADATA
flexion_interpreter-1.0.2.dist-info/WHEEL
flexion_interpreter-1.0.2.dist-info/top_level.txt
flexion_interpreter-1.0.2.dist-info/RECORD
