Metadata-Version: 2.4
Name: flexion-interpreter
Version: 1.0.2
Summary: A Python library for parsing and working with Flexion (.flon) files
Author-email: Error Dev <3rr0r.d3v@gmail.com>
Classifier: Programming Language :: Python :: 3
Classifier: License :: OSI Approved :: MIT License
Classifier: Operating System :: OS Independent
Requires-Python: >=3.7
License-File: LICENSE
Dynamic: license-file
